urwid_timed_progress/__init__.py
urwid_timed_progress-1.1.1.dist-info/DESCRIPTION.rst
urwid_timed_progress-1.1.1.dist-info/METADATA
urwid_timed_progress-1.1.1.dist-info/RECORD
urwid_timed_progress-1.1.1.dist-info/WHEEL
urwid_timed_progress-1.1.1.dist-info/metadata.json
urwid_timed_progress-1.1.1.dist-info/top_level.txt
