Metadata-Version: 2.0
Name: urwid-timed-progress
Version: 1.1.1
Summary: Urwid Timed Progress Bar
Home-page: https://github.com/mgk/urwid_timed_progress/blob/master/README.rst
Author: Michael Keirnan
Author-email: michael@keirnan.com
License: MIT
Keywords: ui widget curses progress bar
Platform: any
Classifier: Development Status :: 5 - Production/Stable
Classifier: Intended Audience :: Developers
Classifier: Environment :: Console
Classifier: Environment :: Console :: Curses
Classifier: License :: OSI Approved :: MIT License
Classifier: Natural Language :: English
Classifier: Topic :: Software Development :: Widget Sets
Classifier: Topic :: Software Development :: Libraries :: Python Modules
Classifier: Programming Language :: Python
Classifier: Programming Language :: Python :: 2
Classifier: Programming Language :: Python :: 2.7
Classifier: Programming Language :: Python :: 3
Classifier: Programming Language :: Python :: 3.2
Classifier: Programming Language :: Python :: 3.3
Classifier: Programming Language :: Python :: 3.4
Classifier: Programming Language :: Python :: Implementation :: PyPy
Requires-Dist: urwid (>=1.3.1)
